{
  "_class": "shapePath",
  "booleanOperation": -1,
  "clippingMaskMode": 0,
  "do_objectID": "AE543D3B-F905-4F97-A6D0-9EA2221392FF",
  "edited": true,
  "exportOptions": {
    "_class": "exportOptions",
    "exportFormats": [
    ],
    "includedLayerIds": [
    ],
    "layerOptions": 0,
    "shouldTrim": false
  },
  "frame": {
    "_class": "rect",
    "constrainProportions": false,
    "height": 25.21733098325584,
    "width": 20.74131304934427,
    "x": 6.95277169171504e-14,
    "y": 0
  },
  "hasClippingMask": false,
  "isClosed": true,
  "isFixedToViewport": false,
  "isFlippedHorizontal": false,
  "isFlippedVertical": false,
  "isLocked": false,
  "isVisible": true,
  "layerListExpandedType": 0,
  "maintainScrollPosition": false,
  "name": "Path",
  "nameIsFixed": false,
  "pointRadiusBehaviour": 1,
  "points": [
    {
      "_class": "curvePoint",
      "cornerRadius": 0,
      "curveFrom": "{0.32609974238539347, -0.0018064422611270925}",
      "curveMode": 4,
      "curveTo": "{0.56849403666353782, 0.00039655267270986242}",
      "hasCurveFrom": true,
      "hasCurveTo": false,
      "point": "{0.56849403666353782, 0.00039655267270986242}"
    },
    {
      "_class": "curvePoint",
      "cornerRadius": 0,
      "curveFrom": "{0.12481731093293277, 0.46212987403679107}",
      "curveMode": 4,
      "curveTo": "{0.12736492371283964, 0.15792630816561293}",
      "hasCurveFrom": true,
      "hasCurveTo": true,
      "point": "{0.12445271786712692, 0.35729395811089626}"
    },
    {
      "_class": "curvePoint",
      "cornerRadius": 0,
      "curveFrom": "{0.28018056365565119, 0.62813943357120994}",
      "curveMode": 4,
      "curveTo": "{0.18189094681774148, 0.56139366317609496}",
      "hasCurveFrom": false,
      "hasCurveTo": true,
      "point": "{0.28018056365565119, 0.62813943357120994}"
    },
    {
      "_class": "curvePoint",
      "cornerRadius": 0,
      "curveFrom": "{0.0012705807286444055, 0.9398775434779294}",
      "curveMode": 4,
      "curveTo": "{0.0058488476999951581, 0.93507120224804996}",
      "hasCurveFrom": true,
      "hasCurveTo": false,
      "point": "{0.0058488476999951581, 0.93507120224804996}"
    },
    {
      "_class": "curvePoint",
      "cornerRadius": 0,
      "curveFrom": "{0.0012490330712130356, 0.95810342155434858}",
      "curveMode": 2,
      "curveTo": "{-0.00074887569700798635, 0.94600287145002693}",
      "hasCurveFrom": true,
      "hasCurveTo": true,
      "point": "{0.00025007868710252466, 0.95205314650218753}"
    },
    {
      "_class": "curvePoint",
      "cornerRadius": 0,
      "curveFrom": "{0.011152272788763951, 0.96719196873748636}",
      "curveMode": 4,
      "curveTo": "{0.005181416400747609, 0.96356394185254068}",
      "hasCurveFrom": false,
      "hasCurveTo": true,
      "point": "{0.011152272788763951, 0.96719196873748636}"
    },
    {
      "_class": "curvePoint",
      "cornerRadius": 0,
      "curveFrom": "{0.072463070815959749, 1.0031587471658581}",
      "curveMode": 4,
      "curveTo": "{0.059365228141251371, 0.99614031384525048}",
      "hasCurveFrom": true,
      "hasCurveTo": false,
      "point": "{0.059365228141251371, 0.99614031384525048}"
    },
    {
      "_class": "curvePoint",
      "cornerRadius": 0,
      "curveFrom": "{0.098899851530287977, 0.98979547108190447}",
      "curveMode": 4,
      "curveTo": "{0.089970598357775045, 1.0003489946020188}",
      "hasCurveFrom": false,
      "hasCurveTo": true,
      "point": "{0.098899851530287977, 0.98979547108190447}"
    },
    {
      "_class": "curvePoint",
      "cornerRadius": 0,
      "curveFrom": "{0.43594613947658406, 0.70203359091470008}",
      "curveMode": 4,
      "curveTo": "{0.37660647436061506, 0.67929472835068239}",
      "hasCurveFrom": true,
      "hasCurveTo": false,
      "point": "{0.37660647436061506, 0.67929472835068239}"
    },
    {
      "_class": "curvePoint",
      "cornerRadius": 0,
      "curveFrom": "{0.72110686139293367, 0.71379481467638284}",
      "curveMode": 4,
      "curveTo": "{0.50061970115353638, 0.71380939600714444}",
      "hasCurveFrom": true,
      "hasCurveTo": true,
      "point": "{0.56608338889589371, 0.71379481087637342}"
    },
    {
      "_class": "curvePoint",
      "cornerRadius": 0,
      "curveFrom": "{1.0193779343955542, 0.4249216681322433}",
      "curveMode": 2,
      "curveTo": "{0.86435445923113163, 0.64577055432322816}",
      "hasCurveFrom": true,
      "hasCurveTo": true,
      "point": "{0.9418661968133375, 0.53534611122773579}"
    },
    {
      "_class": "curvePoint",
      "cornerRadius": 0,
      "curveFrom": "{0.86435445923113163, 0.068024256553145174}",
      "curveMode": 2,
      "curveTo": "{1.0193779343955542, 0.28887314274412951}",
      "hasCurveFrom": true,
      "hasCurveTo": true,
      "point": "{0.9418661968133375, 0.17844869964863763}"
    },
    {
      "_class": "curvePoint",
      "cornerRadius": 0,
      "curveFrom": "{0.56608338889589371, 0}",
      "curveMode": 4,
      "curveTo": "{0.72110686139293367, -3.8000094287019883e-09}",
      "hasCurveFrom": false,
      "hasCurveTo": true,
      "point": "{0.56608338889589371, 0}"
    }
  ],
  "resizingConstraint": 63,
  "resizingType": 0,
  "rotation": 0,
  "shouldBreakMaskChain": false,
  "style": {
    "_class": "style",
    "blur": {
      "_class": "blur",
      "center": "{0.5, 0.5}",
      "isEnabled": false,
      "motionAngle": 0,
      "radius": 10,
      "saturation": 1,
      "type": 0
    },
    "borderOptions": {
      "_class": "borderOptions",
      "dashPattern": [
      ],
      "isEnabled": true,
      "lineCapStyle": 0,
      "lineJoinStyle": 0
    },
    "borders": [
    ],
    "colorControls": {
      "_class": "colorControls",
      "brightness": 0,
      "contrast": 1,
      "hue": 0,
      "isEnabled": true,
      "saturation": 1
    },
    "contextSettings": {
      "_class": "graphicsContextSettings",
      "blendMode": 0,
      "opacity": 1
    },
    "do_objectID": "B42F3C71-4DBC-449E-BB4D-28D08C523FA1",
    "endMarkerType": 0,
    "fills": [
      {
        "_class": "fill",
        "color": {
          "_class": "color",
          "alpha": 1,
          "blue": 0.6627450980392157,
          "green": 0.4470588235294117,
          "red": 0.192156862745098
        },
        "contextSettings": {
          "_class": "graphicsContextSettings",
          "blendMode": 0,
          "opacity": 1
        },
        "fillType": 0,
        "gradient": {
          "_class": "gradient",
          "elipseLength": 0,
          "from": "{0.5, 0}",
          "gradientType": 0,
          "stops": [
            {
              "_class": "gradientStop",
              "color": {
                "_class": "color",
                "alpha": 1,
                "blue": 1,
                "green": 1,
                "red": 1
              },
              "position": 0
            },
            {
              "_class": "gradientStop",
              "color": {
                "_class": "color",
                "alpha": 1,
                "blue": 0,
                "green": 0,
                "red": 0
              },
              "position": 1
            }
          ],
          "to": "{0.5, 1}"
        },
        "isEnabled": true,
        "noiseIndex": 0,
        "noiseIntensity": 0,
        "patternFillType": 1,
        "patternTileScale": 1
      }
    ],
    "innerShadows": [
    ],
    "miterLimit": 10,
    "shadows": [
    ],
    "startMarkerType": 0,
    "windingRule": 0
  }
}